{
    "enabled": true,
    "neededInstalledMods": [],
    "neededUninstalledMods": [],
    "spawns": [
        {
            "id": "trapinch-1",
            "pokemon": "trapinch",
            "presets": [
                "natural"
            ],
            "type": "pokemon",
            "context": "grounded",
            "bucket": "rare",
            "level": "10-34",
            "weight": 4.85,
            "condition": {
                "biomes": [
                    "area_zero_biomes:areazero_savana"
                ]
            }
        }
    ]
}